asdfy/__init__.py
asdfy/accessor.py
asdfy/processor.py
asdfy/writer.py
asdfy-0.1.18.dist-info/LICENSE
asdfy-0.1.18.dist-info/METADATA
asdfy-0.1.18.dist-info/WHEEL
asdfy-0.1.18.dist-info/top_level.txt
asdfy-0.1.18.dist-info/RECORD
