Metadata-Version: 2.1
Name: asdfy
Version: 0.1.18
Summary: A parallel processing library for pyasdf.
Home-page: https://github.com/icui/asdfy
Author: Congyue Cui
Author-email: ccui@princeton.edu
License: UNKNOWN
Platform: UNKNOWN
Classifier: Programming Language :: Python :: 3
Classifier: License :: OSI Approved :: MIT License
Classifier: Operating System :: OS Independent
Requires-Python: >=3.8
